streaminghub_proxy_empatica_e4/__init__.py
streaminghub_proxy_empatica_e4/mock.py
streaminghub_proxy_empatica_e4/node.json
streaminghub_proxy_empatica_e4/proxy.py
streaminghub_proxy_empatica_e4/util.py
streaminghub_proxy_empatica_e4-0.0.1.dist-info/METADATA
streaminghub_proxy_empatica_e4-0.0.1.dist-info/WHEEL
streaminghub_proxy_empatica_e4-0.0.1.dist-info/entry_points.txt
streaminghub_proxy_empatica_e4-0.0.1.dist-info/top_level.txt
streaminghub_proxy_empatica_e4-0.0.1.dist-info/RECORD
